mkAppleOpenSourceDownload/__init__.py
mkAppleOpenSourceDownload/download.py
mkAppleOpenSourceDownload-1.4.data/scripts/aosdownload
mkAppleOpenSourceDownload-1.4.dist-info/LICENSE
mkAppleOpenSourceDownload-1.4.dist-info/METADATA
mkAppleOpenSourceDownload-1.4.dist-info/WHEEL
mkAppleOpenSourceDownload-1.4.dist-info/top_level.txt
mkAppleOpenSourceDownload-1.4.dist-info/RECORD
